midas/__init__.py
midas/__main__.py
midas/common/__init__.py
midas/common/argparser.py
midas/common/bowtie2.py
midas/common/snvs.py
midas/common/utilities.py
midas/common/utils.py
midas/models/__init__.py
midas/models/midasdb.py
midas/models/sample.py
midas/models/samplepool.py
midas/models/species.py
midas/params/__init__.py
midas/params/batch.py
midas/params/inputs.py
midas/params/outputs.py
midas/params/schemas.py
midas/subcommands/__init__.py
midas/subcommands/annotate_genome.py
midas/subcommands/annotate_pangenome.py
midas/subcommands/augment_pangenome.py
midas/subcommands/aws_batch_init.py
midas/subcommands/aws_batch_submit.py
midas/subcommands/build_bowtie2db.py
midas/subcommands/build_midasdb.py
midas/subcommands/build_pangenome.py
midas/subcommands/compute_chunks.py
midas/subcommands/database.py
midas/subcommands/enhance_pangenome.py
midas/subcommands/example_subcommand.py
midas/subcommands/import_genome.py
midas/subcommands/infer_markers.py
midas/subcommands/init.py
midas/subcommands/merge_genes.py
midas/subcommands/merge_snps.py
midas/subcommands/merge_species.py
midas/subcommands/parse_panannot.py
midas/subcommands/prune_centroids.py
midas/subcommands/recluster_centroids.py
midas/subcommands/run_genes.py
midas/subcommands/run_snps.py
midas/subcommands/run_species.py
midasv3-1.0.1.dist-info/LICENSE
midasv3-1.0.1.dist-info/METADATA
midasv3-1.0.1.dist-info/WHEEL
midasv3-1.0.1.dist-info/entry_points.txt
midasv3-1.0.1.dist-info/top_level.txt
midasv3-1.0.1.dist-info/RECORD
